.gitignore
LICENSE
README.md
publish.sh
requirements.txt
setup.cfg
setup.py
docs/Makefile
docs/conf.py
docs/index.rst
docs/api/pykafka_tools.rst
pykafka_tools/__init__.py
pykafka_tools/avro_coding.py
pykafka_tools/event.py
pykafka_tools/kafka_consumer.py
pykafka_tools/kafka_producer_pool.py
pykafka_tools/postgres_connector.py
pykafka_tools.egg-info/PKG-INFO
pykafka_tools.egg-info/SOURCES.txt
pykafka_tools.egg-info/dependency_links.txt
pykafka_tools.egg-info/requires.txt
pykafka_tools.egg-info/top_level.txt