Metadata-Version: 1.1
Name: pykafka-tools
Version: 0.1.8
Summary: The pykafka-tools extend the functionalities of python pykafka module.
Home-page: https://github.com/smueller18/pykafka-tools
Author: Stephan Müller
Author-email: stephan@mueller5.eu
License: MIT
Download-URL: https://github.com/smueller18/pykafka-tools
Platform: UNKNOWN
Classifier: Development Status :: 3 - Alpha
Classifier: Programming Language :: Python :: 2.7
Classifier: Programming Language :: Python :: 3.5
Classifier: License :: OSI Approved :: MIT License
